pbipinspect/__init__.py
pbipinspect/expectations.py
pbipinspect/inspect.py
pbipinspect/pbip.py
pbipinspect/tmdl.py
pbipinspect/tmsl.py
pbipinspect/utils.py
pbipinspect-0.1.0.dist-info/LICENSE
pbipinspect-0.1.0.dist-info/METADATA
pbipinspect-0.1.0.dist-info/WHEEL
pbipinspect-0.1.0.dist-info/RECORD
