Metadata-Version: 2.1
Name: pbipinspect
Version: 0.1.0
Summary: Parse, validate and document your Power BI Project
Home-page: https://github.com/matheussrod/pbipinspect
License: MIT
Author: Matheus S. Rodrigues
Author-email: matheus.srodr@gmail.com
Requires-Python: >=3.11,<4.0
Classifier: License :: OSI Approved :: MIT License
Classifier: Programming Language :: Python :: 3
Classifier: Programming Language :: Python :: 3.11
Classifier: Programming Language :: Python :: 3.12
Classifier: Programming Language :: Python :: 3.13
Project-URL: Repository, https://github.com/matheussrod/pbipinspect
